{
  "id": "8e45b627-0dea-a624-ecc0-ed8f951f02b7",
  "name": "Play copy",
  "values": [
    {
      "enabled": true,
      "key": "baseurl",
      "value": "https://play.railsbank.com",
      "type": "text"
    },
    {
      "enabled": true,
      "key": "customer_api_key",
      "value": "API-Key abcdef",
      "type": "text"
    },
    {
      "enabled": true,
      "key": "test_info",
      "value": "2017-12-12T11:00:13.129Z | 0.15",
      "type": "text"
    },
    {
      "enabled": true,
      "key": "enduser_id",
      "value": "5a1fe4bd-0fd6-45fb-8680-19b11d88cc41",
      "type": "text"
    },
    {
      "enabled": true,
      "key": "euroledger_prodref",
      "value": "ExampleBank-EUR-1",
      "type": "text"
    },
    {
      "enabled": true,
      "key": "iban",
      "value": "SK5500000011512039376272",
      "type": "text"
    },
    {
      "enabled": true,
      "key": "current_balance",
      "value": "0",
      "type": "text"
    },
    {
      "enabled": true,
      "key": "beneficiary_id",
      "value": "5a1fe3db-0092-4d1c-9049-60c15b006f10",
      "type": "text"
    },
    {
      "enabled": true,
      "key": "date_set_for_payment",
      "value": "2017-12-12",
      "type": "text"
    },
    {
      "enabled": true,
      "key": "transaction_id_no_fixed_time",
      "value": "5a1fe3de-3e7c-4d1d-b16a-faf41450cca4",
      "type": "text"
    },
    {
      "enabled": true,
      "key": "transaction_id_fixed_time",
      "value": "59f3425e-5259-46ce-b0b9-6debdb2ab048",
      "type": "text"
    },
    {
      "enabled": true,
      "key": "ledger_id",
      "value": "5a1fe3c8-5114-43ee-b614-eff1452e29b8",
      "type": "text"
    },
    {
      "enabled": true,
      "key": "second_ledger_id",
      "value": "5a1fe3de-5fa9-43ad-9c22-9e1e288c719d",
      "type": "text"
    },
    {
      "enabled": true,
      "key": "second_ledger_amount",
      "value": "0",
      "type": "text"
    },
    {
      "enabled": true,
      "key": "starlingledger_prodref",
      "value": "ExampleBank-GBP-1",
      "type": "text"
    },
    {
      "enabled": true,
      "key": "eur_iban_1",
      "value": "SK9100000031511266394816",
      "type": "text"
    },
    {
      "enabled": true,
      "key": "bic_swift_1",
      "value": "SPSRSKBA",
      "type": "text"
    },
    {
      "enabled": true,
      "key": "pseudocredit_tx",
      "value": "5a14185b-c05c-4739-b760-c03eb9cf666d",
      "type": "text"
    }
  ],
  "timestamp": 1513098046535,
  "_postman_variable_scope": "environment",
  "_postman_exported_at": "2017-12-12T17:00:49.494Z",
  "_postman_exported_using": "Postman/5.4.1"
}